simplenetlink/__init__.py
simplenetlink-0.7.dist-info/LICENSE
simplenetlink-0.7.dist-info/METADATA
simplenetlink-0.7.dist-info/WHEEL
simplenetlink-0.7.dist-info/top_level.txt
simplenetlink-0.7.dist-info/RECORD
