Metadata-Version: 2.1
Name: simplenetlink
Version: 0.7
Summary: Abstraction layer for for simplified usage of pyroute2
Home-page: https://github.com/jinjamator/simplenetlink
Author: Wilhelm Putz
Author-email: wp@aci.guru
License: ASL V2
Classifier: License :: OSI Approved :: Apache Software License
Classifier: Programming Language :: Python :: 3.7
Classifier: Programming Language :: Python :: 3.8
Classifier: Topic :: System :: Installation/Setup
Classifier: Topic :: System :: Systems Administration
Classifier: Topic :: Utilities
Requires-Python: >=3.7
License-File: LICENSE
Requires-Dist: pyroute2
